{
  "jobs": [
    {
      "id": 1,
      "Company": "zinny",
      "postedAt": "2021-09-09",
      "city": "ludhiana",
      "location": "Belgium",
      "Role": "FullStack",
      "level": "Junior",
      "contract": "Full Time",
      "position": "Junior Frontend Developer",
      "language": "Java"
    },
    {
      "Company": "gigin",
      "city": "delhi",
      "location": "bhopal",
      "Role": "backend",
      "level": "Senior",
      "position": "nodejs developer",
      "Language": "java",
      "Contract": "full time",
      "postedAt": "2022-11-23",
      "id": 2
    },
    {
      "Company": "shree gold",
      "city": "sagar",
      "location": "sagar",
      "Role": "Frontend",
      "level": "Junior",
      "position": "Frondend dev",
      "Language": "javaScript",
      "Contract": "full time",
      "postedAt": "2022-11-29",
      "id": 3
    },
    {
      "Company": "LL",
      "city": "SA",
      "location": "AS",
      "Role": "Frontend",
      "level": "Junior",
      "position": "ADS",
      "Language": "ASD",
      "Contract": "full time",
      "postedAt": "2022-11-29",
      "id": 4
    }
  ]
}